CellOrientationLinearElasticity/__init__.py
orientation/__init__.py
orientation/single_strain.py
orientation/strain_addition.py
simulation/__init__.py
simulation/simulation.py
CellOrientationLinearElasticity-1.0.dist-info/LICENSE
CellOrientationLinearElasticity-1.0.dist-info/METADATA
CellOrientationLinearElasticity-1.0.dist-info/WHEEL
CellOrientationLinearElasticity-1.0.dist-info/top_level.txt
CellOrientationLinearElasticity-1.0.dist-info/RECORD
